quick_django_docker_setup/__init__.py
quick_django_docker_setup/celery.py
quick_django_docker_setup/django_project.py
quick_django_docker_setup/docker_compose.py
quick_django_docker_setup/dockerfile.py
quick_django_docker_setup/env_file.py
quick_django_docker_setup/main.py
quick_django_docker_setup/package_manager.py
quick_django_docker_setup/settings.py
quick_django_docker_setup/urls.py
quick_django_docker_setup/utils.py
quick_django_docker_setup/text_to_insert/__init__.py
quick_django_docker_setup/text_to_insert/celery_to_insert.py
quick_django_docker_setup/text_to_insert/docker_compose_to_insert.py
quick_django_docker_setup/text_to_insert/dockerfile_to_insert.py
quick_django_docker_setup/text_to_insert/env_file_to_insert.py
quick_django_docker_setup/text_to_insert/settings_to_insert.py
quick_django_docker_setup/text_to_insert/urls_to_insert.py
quick_django_docker_setup-0.4.0.dist-info/LICENSE
quick_django_docker_setup-0.4.0.dist-info/METADATA
quick_django_docker_setup-0.4.0.dist-info/WHEEL
quick_django_docker_setup-0.4.0.dist-info/entry_points.txt
quick_django_docker_setup-0.4.0.dist-info/top_level.txt
quick_django_docker_setup-0.4.0.dist-info/RECORD
