Metadata-Version: 2.1
Name: quick-django-docker-setup
Version: 0.4.0
Summary: Quick setup for Django development with Docker, Postgres, Celery and more
License: GNU GENERAL PUBLIC LICENSE
Project-URL: Source, https://github.com/KrzysztofCzapla/quick-django-docker-setup
Keywords: quick,django,docker,setup
License-File: LICENSE
